README.rst
setup.cfg
setup.py
stub.py
stub.egg-info/PKG-INFO
stub.egg-info/SOURCES.txt
stub.egg-info/dependency_links.txt
stub.egg-info/requires.txt
stub.egg-info/top_level.txt
stubbing/__init__.py
stubbing/expect.py