Metadata-Version: 1.0
Name: stub
Version: 0.2
Summary: Temporarily modify callable behaviour and object attributes.
Home-page: https://bitbucket.org/ilowe/stub
Author: Iain Lowe
Author-email: iain.lowe@gmail.com
License: MIT
Keywords: test testing stub mock virtual simulate decorate
Platform: UNKNOWN
